{"authorDailyContributionsMap":{"elijah-ng":[],"Chen-Beitian":[],"MrMarshall12":[],"BenedTj":[],"DenseLance-alt":[]},"authorFileTypeContributionMap":{"elijah-ng":{"docs":0,"functional-code":0,"test-code":0},"Chen-Beitian":{"docs":0,"functional-code":0,"test-code":0},"MrMarshall12":{"docs":0,"functional-code":0,"test-code":0},"BenedTj":{"docs":0,"functional-code":0,"test-code":0},"DenseLance-alt":{"docs":0,"functional-code":0,"test-code":0}},"authorContributionVariance":{"elijah-ng":0.0,"Chen-Beitian":0.0,"MrMarshall12":0.0,"BenedTj":0.0,"DenseLance-alt":0.0},"authorDisplayNameMap":{"elijah-ng":"CS2103T-W14-2 ELIJ.. JIE","Chen-Beitian":"CS2103T-W14-2 CHEN..TIAN","MrMarshall12":"CS2103T-W14-2 ACHM..ABIL","BenedTj":"CS2103T-W14-2 BENE..TJIA","DenseLance-alt":"CS2103T-W14-2 CHIN..ANCE"}}
