{"authorDailyContributionsMap":{"GuoxintongMark":[],"HoneyGlazedPorkChops":[],"EepyAdventure":[],"Echoandland":[]},"authorFileTypeContributionMap":{"GuoxintongMark":{"docs":0,"functional-code":0,"test-code":0},"HoneyGlazedPorkChops":{"docs":0,"functional-code":0,"test-code":0},"EepyAdventure":{"docs":0,"functional-code":0,"test-code":0},"Echoandland":{"docs":0,"functional-code":0,"test-code":0}},"authorContributionVariance":{"GuoxintongMark":0.0,"HoneyGlazedPorkChops":0.0,"EepyAdventure":0.0,"Echoandland":0.0},"authorDisplayNameMap":{"GuoxintongMark":"CS2103T-W11-4 GUO ..TONG","HoneyGlazedPorkChops":"CS2103T-W11-4 EUGE.. YOU","EepyAdventure":"CS2103T-W11-4 POON..SHUA","Echoandland":"CS2103T-W11-4 WANG..HENG"}}
