{"authorDailyContributionsMap":{"JIMAI1228":[{"date":"2026-04-13T00:00:00","commitResults":[{"hash":"9de8b746e9180689445694d52f1aacdde44b2d13","isMergeCommit":false,"messageTitle":"Fix incorrect find command format in help window","messageBody":"","fileTypesAndContributionMap":{"functional-code":{"insertions":1,"deletions":1}}}]}],"Hack-Zac":[{"date":"2026-04-12T00:00:00","commitResults":[{"hash":"36174e93e2167b9087a0b17ad8bd7886613656d6","isMergeCommit":true,"messageTitle":"Merge pull request #403 from SUN-HEQIAO/UG-DG-1.6.1","messageBody":"UG-DG-Clarity and Typos-1.6.1","fileTypesAndContributionMap":{}},{"hash":"7b449ca839bdfae24c12a3fb79638a79539056ae","isMergeCommit":true,"messageTitle":"Merge pull request #410 from SUN-HEQIAO/402.3","messageBody":"Fix issue 402","fileTypesAndContributionMap":{}}]}],"JLM012":[{"date":"2026-04-13T00:00:00","commitResults":[{"hash":"2d5a320ec71488c691e3eee70d527f0f769d2577","isMergeCommit":false,"messageTitle":"update AddressBook.java","messageBody":"","fileTypesAndContributionMap":{"functional-code":{"insertions":29,"deletions":4}}},{"hash":"d3f296f2d17e55aeecee40b858a167cfba0347ff","isMergeCommit":false,"messageTitle":"Update JsonSerializableAddressBook","messageBody":"","fileTypesAndContributionMap":{"functional-code":{"insertions":6,"deletions":1}}},{"hash":"caab627e084ce1661d50220fffe4982a8feeeb89","isMergeCommit":false,"messageTitle":"Update-JsonSerializabeeeAddressBook","messageBody":"","fileTypesAndContributionMap":{"functional-code":{"insertions":8,"deletions":0}}},{"hash":"15fd823f89f0bb5808477990529e81ca405b54bf","isMergeCommit":false,"messageTitle":"Update AddressBookTest.java","messageBody":"","fileTypesAndContributionMap":{"test-code":{"insertions":23,"deletions":0}}},{"hash":"3b4caafe45a658a2e709d7e16ab7a2ec0ecbe4d3","isMergeCommit":false,"messageTitle":"Update JsonAddressBookStorageTest","messageBody":"","fileTypesAndContributionMap":{"test-code":{"insertions":19,"deletions":7}}},{"hash":"1cb30d28789c22d280040677a0f235d4c170fcb1","isMergeCommit":false,"messageTitle":"Update Storage tests","messageBody":"","fileTypesAndContributionMap":{"test-code":{"insertions":6,"deletions":2}}},{"hash":"abe11fa1ad89519450cc430c8d3365eb0fbaf167","isMergeCommit":false,"messageTitle":"Fix trailing whitespace","messageBody":"","fileTypesAndContributionMap":{"functional-code":{"insertions":0,"deletions":1}}},{"hash":"aa2dfe1f7d650299bd49545f6fcbe0e4c5a45ff9","isMergeCommit":true,"messageTitle":"Merge pull request #411 from SUN-HEQIAO/402.3","messageBody":"Fix issue 402-Enhanced","fileTypesAndContributionMap":{}}]}],"agukaGorilla":[{"date":"2026-04-12T00:00:00","commitResults":[{"hash":"0ccfb2287938e9726021172d3e23cd753e200921","isMergeCommit":false,"messageTitle":"Add tir-breaker to sort","messageBody":"","fileTypesAndContributionMap":{"functional-code":{"insertions":11,"deletions":6},"docs":{"insertions":0,"deletions":1}}},{"hash":"a159c7c1ae5f45afc5c3d2c6b2f58050e0471d36","isMergeCommit":false,"messageTitle":"Style check","messageBody":"","fileTypesAndContributionMap":{"docs":{"insertions":1,"deletions":0}}}]}],"SUN-HEQIAO":[{"date":"2026-04-12T00:00:00","commitResults":[{"hash":"3adc9c3eefdeccc5911b44869b7554e0a71f3136","isMergeCommit":false,"messageTitle":"Fix issue 378","messageBody":"","fileTypesAndContributionMap":{"functional-code":{"insertions":11,"deletions":6},"test-code":{"insertions":26,"deletions":0}}},{"hash":"e70096f29284b03457e8a03a8db803969b2d0f67","isMergeCommit":false,"messageTitle":"Fix issue 364","messageBody":"","fileTypesAndContributionMap":{"docs":{"insertions":2,"deletions":1}}},{"hash":"220b72c174f8e817893bd9fb1febd96e0274e34e","isMergeCommit":false,"messageTitle":"Fix issue 365","messageBody":"","fileTypesAndContributionMap":{"docs":{"insertions":2,"deletions":3}}},{"hash":"ef7ae963f9f7bd8ab953d788f0c20c9b1bcaa605","isMergeCommit":false,"messageTitle":"Fix issue 366","messageBody":"","fileTypesAndContributionMap":{"docs":{"insertions":2,"deletions":1}}},{"hash":"6e8033b1a4cf2b7ef2f96d36f9e91f58fd126464","isMergeCommit":false,"messageTitle":"Fix issue 388","messageBody":"","fileTypesAndContributionMap":{"docs":{"insertions":2,"deletions":1}}},{"hash":"f6e4e448236e627e510222baaec78d0d8fbd80ad","isMergeCommit":false,"messageTitle":"Fix issue 385","messageBody":"","fileTypesAndContributionMap":{"docs":{"insertions":5,"deletions":3}}},{"hash":"4a4ea78dfed91f774abc15beb5385f8ebd906ce1","isMergeCommit":false,"messageTitle":"Fix issue 393","messageBody":"","fileTypesAndContributionMap":{"docs":{"insertions":4,"deletions":4}}},{"hash":"e3212b732e3e119de9ccbad026968d84e07cc7f2","isMergeCommit":false,"messageTitle":"Fix issue 397","messageBody":"","fileTypesAndContributionMap":{"docs":{"insertions":12,"deletions":3}}},{"hash":"d3d0781c4d4de25da21fa0c4cfef68a0a68e92f8","isMergeCommit":false,"messageTitle":"\"parts\" to \"either\"","messageBody":"","fileTypesAndContributionMap":{"docs":{"insertions":1,"deletions":1}}},{"hash":"8095b2595b6f81e535dbadf6d60367ffba4bc83a","isMergeCommit":false,"messageTitle":"\"parts\" to \"either\"","messageBody":"","fileTypesAndContributionMap":{"docs":{"insertions":1,"deletions":1}}},{"hash":"97046eceaa4e6946b0472efa78a27e2572136eea","isMergeCommit":false,"messageTitle":"\"an\" to \"a\"","messageBody":"","fileTypesAndContributionMap":{"docs":{"insertions":1,"deletions":1}}},{"hash":"e4818f48a71ae3c4ce71a9413847741a5184274c","isMergeCommit":true,"messageTitle":"Merge pull request #405 from SUN-HEQIAO/UG-DG-1.6.1","messageBody":"Ug dg 1.6.1","fileTypesAndContributionMap":{}},{"hash":"90bf5d1d02b000843861c99e261b41d3912b9cf7","isMergeCommit":true,"messageTitle":"Merge pull request #406 from SUN-HEQIAO/378.1","messageBody":"Fix issue 378","fileTypesAndContributionMap":{}},{"hash":"10696848120db95479c07ee7d15abf6a55f7f40a","isMergeCommit":true,"messageTitle":"Merge pull request #408 from agukaGorilla/branch-bug-sort","messageBody":"Add tie-breaker to sort","fileTypesAndContributionMap":{}},{"hash":"880dc3342ad006dc94e240c72c457d6ebe3b0e67","isMergeCommit":false,"messageTitle":"Fix issue 402","messageBody":"","fileTypesAndContributionMap":{"functional-code":{"insertions":14,"deletions":7},"test-code":{"insertions":10,"deletions":6}}},{"hash":"4fd38d0a427cadfa7888e1d95a5d829b3289355a","isMergeCommit":false,"messageTitle":"Fix issue 402-Enhanced","messageBody":"","fileTypesAndContributionMap":{"functional-code":{"insertions":24,"deletions":8},"test-code":{"insertions":20,"deletions":13}}},{"hash":"58db3a61b7f6de346b05b0873fb89decd6f48123","isMergeCommit":false,"messageTitle":"Fix issue 402-Enhanced","messageBody":"","fileTypesAndContributionMap":{"functional-code":{"insertions":1,"deletions":1}}}]},{"date":"2026-04-13T00:00:00","commitResults":[{"hash":"f7daa7e86450fce95f61da62d2bff0faa0f9841a","isMergeCommit":true,"messageTitle":"Merge pull request #413 from JLM012/Bug-Fix-#383","messageBody":" Ensure that membership ID is always increasing even after user exits the app","fileTypesAndContributionMap":{}},{"hash":"af45f359a2b41e5e9a25b4a29ab09dff9eb52dda","isMergeCommit":true,"messageTitle":"Merge branch \u0027master\u0027 into 402.3","messageBody":"# Conflicts:\n#\tsrc/main/java/seedu/address/model/AddressBook.java\n","fileTypesAndContributionMap":{}}]},{"date":"2026-04-14T00:00:00","commitResults":[{"hash":"086d637a82f2f6c2988bb69474ad8d1106b515bc","isMergeCommit":false,"messageTitle":"Update UG\u0027s FAQ, Known Issues, README, and fix","messageBody":"","fileTypesAndContributionMap":{"docs":{"insertions":4,"deletions":2}}},{"hash":"4d001c1cca55d63305cec9f390c5abbf116540ba","isMergeCommit":true,"messageTitle":"Merge pull request #418 from SUN-HEQIAO/UG-1.6.2","messageBody":"Update UG\u0027s FAQ, Known Issues, README, and fix","fileTypesAndContributionMap":{}},{"hash":"093cc6d169aedc23f6c7ca8adc3426b3b04e74d7","isMergeCommit":true,"messageTitle":"Merge pull request #417 from JIMAI1228/issue-382-incorrectFindFormat","messageBody":"Fix incorrect find command format in help window","fileTypesAndContributionMap":{}},{"hash":"6b2690a3f2163ae9af4852f22d220426db7d3a47","isMergeCommit":false,"messageTitle":"Update UG\u0027s FAQ, Known Issues, README, and fix","messageBody":"","fileTypesAndContributionMap":{"docs":{"insertions":0,"deletions":2}}},{"hash":"a6d58bee6988396de855cea7c74db90e42761c0f","isMergeCommit":true,"messageTitle":"Merge pull request #419 from SUN-HEQIAO/UG-1.6.2","messageBody":"Update UG\u0027s FAQ, Known Issues, README, and fix","fileTypesAndContributionMap":{}}]}]},"authorFileTypeContributionMap":{"JIMAI1228":{"docs":0,"functional-code":1,"test-code":0},"Hack-Zac":{"docs":0,"functional-code":0,"test-code":0},"JLM012":{"docs":0,"functional-code":40,"test-code":47},"agukaGorilla":{"docs":0,"functional-code":11,"test-code":0},"SUN-HEQIAO":{"docs":27,"functional-code":49,"test-code":56}},"authorContributionVariance":{"JIMAI1228":0.25,"Hack-Zac":0.0,"JLM012":702.25,"agukaGorilla":22.5625,"SUN-HEQIAO":2652.25},"authorDisplayNameMap":{"JIMAI1228":"CS2103T-W08-4 ZHOU..GBIN","Hack-Zac":"CS2103T-W08-4 ISAA..AHAM","JLM012":"CS2103T-W08-4 JASH..MING","agukaGorilla":"CS2103T-W08-4 SENT.. RAM","SUN-HEQIAO":"CS2103T-W08-4 SUN ..QIAO"}}
